funcipy/__init__.py
funcipy/funcipy.py
funcipy-0.5.dist-info/DESCRIPTION.rst
funcipy-0.5.dist-info/METADATA
funcipy-0.5.dist-info/RECORD
funcipy-0.5.dist-info/WHEEL
funcipy-0.5.dist-info/metadata.json
funcipy-0.5.dist-info/top_level.txt
