Metadata-Version: 2.0
Name: funcipy
Version: 0.5
Summary: A library to inject common functional programming operations as methods into iterable objects.
Home-page: https://bitbucket.org/rvprasad/funcipy
Author: Venkatesh-Prasad Ranganath
Author-email: UNKNOWN
License: BSD 3-Clause License
Download-URL: https://bitbucket.org/rvprasad/funcipy/downloads/?tab=tags
Keywords: functional,programming
Platform: unix
Platform: linux
Platform: osx
Platform: cygwin
Platform: win32
Classifier: Intended Audience :: Developers
Classifier: Topic :: Software Development :: Libraries
Classifier: Development Status :: 5 - Production/Stable
Classifier: License :: OSI Approved :: BSD License
Classifier: Operating System :: OS Independent
Classifier: Programming Language :: Python :: 3.5
Classifier: Programming Language :: Python :: 3.6
